hwmcp_test/__init__.py
hwmcp_test/main.py
hwmcp_test-0.1.1.dist-info/METADATA
hwmcp_test-0.1.1.dist-info/WHEEL
hwmcp_test-0.1.1.dist-info/entry_points.txt
hwmcp_test-0.1.1.dist-info/top_level.txt
hwmcp_test-0.1.1.dist-info/RECORD
